setup.cfg
setup.py
naakh/__init__.py
naakh/api_client.py
naakh/configuration.py
naakh/rest.py
naakh.egg-info/PKG-INFO
naakh.egg-info/SOURCES.txt
naakh.egg-info/dependency_links.txt
naakh.egg-info/pbr.json
naakh.egg-info/requires.txt
naakh.egg-info/top_level.txt
naakh/apis/__init__.py
naakh/apis/languages_api.py
naakh/apis/oauth_api.py
naakh/apis/tones_api.py
naakh/apis/topics_api.py
naakh/apis/translate_api.py
naakh/apis/translatedtext_api.py
naakh/apis/translation_api.py
naakh/models/__init__.py
naakh/models/access_token_creation_payload.py
naakh/models/access_token_response_payload.py
naakh/models/error.py
naakh/models/language.py
naakh/models/languages_resource.py
naakh/models/meta.py
naakh/models/metadata.py
naakh/models/naakh_error.py
naakh/models/simple_translation_request.py
naakh/models/tone.py
naakh/models/tones_resource.py
naakh/models/topic.py
naakh/models/topics_resource.py
naakh/models/translated_text.py
naakh/models/translated_text_update_payload.py
naakh/models/translation_progress.py
naakh/models/translation_request.py
naakh/models/translation_request_creation_payload.py