Metadata-Version: 1.1
Name: naakh
Version: 0.0.4
Summary: Naakh Translations
Home-page: https://github.com/Naakh/naakh-py
Author: Rohith Salim
Author-email: rohitsalim@gmail.com
License: UNKNOWN
Download-URL: https://github.com/Naakh/naakh-py/tarball/0.0.4
Keywords: Swagger,Naakh Translations
Platform: UNKNOWN
